chat_replay_downloader/__init__.py
chat_replay_downloader/__main__.py
chat_replay_downloader/chat_replay_downloader.py
chat_replay_downloader/cli.py
chat_replay_downloader/errors.py
chat_replay_downloader/utils.py
chat_replay_downloader/formatting/__init__.py
chat_replay_downloader/formatting/custom_formats.json
chat_replay_downloader/formatting/format.py
chat_replay_downloader/output/__init__.py
chat_replay_downloader/output/continuous_write.py
chat_replay_downloader/sites/__init__.py
chat_replay_downloader/sites/common.py
chat_replay_downloader/sites/facebook.py
chat_replay_downloader/sites/twitch.py
chat_replay_downloader/sites/youtube.py
chat_replay_downloader-0.0.9.dist-info/AUTHORS.md
chat_replay_downloader-0.0.9.dist-info/LICENSE
chat_replay_downloader-0.0.9.dist-info/METADATA
chat_replay_downloader-0.0.9.dist-info/WHEEL
chat_replay_downloader-0.0.9.dist-info/entry_points.txt
chat_replay_downloader-0.0.9.dist-info/top_level.txt
chat_replay_downloader-0.0.9.dist-info/RECORD
