Metadata-Version: 2.1
Name: chat-replay-downloader
Version: 0.0.9
Summary: A simple tool used to retrieve chat messages from livestreams, videos, clips and past broadcasts. No authentication needed!
Home-page: https://github.com/xenova/chat-replay-downloader
Author: Joshua Lochner
Author-email: admin@xenova.com
License: MIT license
Keywords: chat_replay_downloader
Platform: UNKNOWN
Classifier: Development Status :: 2 - Pre-Alpha
Classifier: Intended Audience :: Developers
Classifier: License :: OSI Approved :: MIT License
Classifier: Natural Language :: English
Classifier: Programming Language :: Python :: 3
Classifier: Programming Language :: Python :: 3.5
Classifier: Programming Language :: Python :: 3.6
Classifier: Programming Language :: Python :: 3.7
Classifier: Programming Language :: Python :: 3.8
Classifier: Operating System :: OS Independent
Requires-Python: >=3.5
Requires-Dist: requests
Requires-Dist: datetime
Requires-Dist: isodate
Requires-Dist: regex
Requires-Dist: argparse
Requires-Dist: docstring-parser
Requires-Dist: colorlog
